recaptcha_cracker/__init__.py
recaptcha_cracker/audio_manager.py
recaptcha_cracker/cracker.py
recaptcha_cracker/recaptcha_v2.py
recaptcha_cracker/text_captcha.py
recaptcha_cracker/utils/__init__.py
recaptcha_cracker/utils/audio_manager.py
recaptcha_cracker-0.2.1.dist-info/LICENSE
recaptcha_cracker-0.2.1.dist-info/METADATA
recaptcha_cracker-0.2.1.dist-info/WHEEL
recaptcha_cracker-0.2.1.dist-info/top_level.txt
recaptcha_cracker-0.2.1.dist-info/RECORD
