Metadata-Version: 2.1
Name: recaptcha-cracker
Version: 0.2.1
Summary: captcha_cracker - A complete Python package for solving various types of CAPTCHAs, including text CAPTCHAs, reCAPTCHAs, and more. Enhance your automation scripts with robust CAPTCHA resolution capabilities.
Home-page: https://github.com/wipodev/Recaptcha_Cracker
Author: Wipodev
Author-email: ajwipo@gmail.com
License: MIT
Project-URL: Documentation, https://github.com/wipodev/Recaptcha_Cracker/blob/main/README.md
Project-URL: Source, https://github.com/wipodev/Recaptcha_Cracker
Project-URL: Bug Tracker, https://github.com/wipodev/Recaptcha_Cracker/issues
Keywords: python,captcha,speech recognition,selenium,web automation,recaptcha
Classifier: Programming Language :: Python :: 3
Classifier: License :: OSI Approved :: MIT License
Classifier: Operating System :: OS Independent
Requires-Python: >=3.10
License-File: LICENSE
Requires-Dist: seleniumbase ~=4.25.4
Requires-Dist: pydub ~=0.25.1
Requires-Dist: SpeechRecognition ~=3.10.3
Requires-Dist: verbose-terminal ~=1.0.1
Requires-Dist: easyocr ~=1.7.1
